[
  { "id": 1.0, "demand": 3.0, "lat": 40.518348, "lng": -3.897235 },
  { "id": 2.0, "demand": 5.0, "lat": 40.519669, "lng": -3.900518 },
  { "id": 3.0, "demand": 8.0, "lat": 40.520794, "lng": -3.896012 },
  { "id": 4.0, "demand": 2.0, "lat": 40.519228, "lng": -3.891806 },
  { "id": 5.0, "demand": 1.0, "lat": 40.522425, "lng": -3.894338 },
  { "id": 6.0, "demand": 4.0, "lat": 40.523681, "lng": -3.892622 },
  { "id": 7.0, "demand": 6.0, "lat": 40.523535, "lng": -3.890347 },
  { "id": 8.0, "demand": 2.0, "lat": 40.526291, "lng": -3.893652 }
]
